{
    "microchip": {"name": "microchip", "color": "blue"},
    "code": {"name": "code", "color": "green"},
    "3d_parts": {"name": "cube", "color": "purple"},
    "cube": {"name": "cube", "color": "purple"},
    "power": {"name": "bolt", "color": "yellow"},
    "gauge": {"name": "tachometer-alt", "color": "blue"},
    "battery": {"name": "battery-three-quarters", "color": "green"},
    "scale": {"name": "weight", "color": "purple"},
    "circuit": {"name":"circle-nodes", "color":"teal"},
    "test": {"name":"vial-circle-check", "color":"green"},
    "plug": {"name":"plug", "color":"blue"},
    "bluetooth": {"name": "bluetooth-b fa-brands", "color": "blue"},
    "sound": {"name": "volume-high", "color": "violet"},
    "user-lock": {"name": "user-lock", "color": "orange"},
    "lock": {"name": "lock", "color": "violet"},
    "map": {"name": "map", "color": "green"},
    "wifi": {"name": "wifi", "color": "blue"},
    "puzzle-piece": {"name": "puzzle-piece", "color": "yellow"},
    "ui": {"name": "users-viewfinder", "color": "teal"},
    "user": {"name": "user", "color": "orange"},
    "settings": {"name": "fa-solid fa-gears", "color": "blue"},
    "function": {"name": "fa-solid fa-gears", "color": "blue"},
    "gears": {"name": "fa-solid fa-gears", "color": "blue"},
    "server": {"name": "fa-solid fa-server", "color": "purple"},
    "database": {"name": "fa-solid fa-database", "color": "blue"},
    "idea": {"name": "lightbulb", "color": "yellow"},
    "fire": {"name": "fire", "color": "red"},
    "home": {"name": "house", "color": "blue"},

    "missingIcon": {"name":"notdef", "color":"fuchsia"}
}

